llama_index/readers/youtube_metadata/BUILD
llama_index/readers/youtube_metadata/__init__.py
llama_index/readers/youtube_metadata/base.py
llama_index_readers_youtube_metadata-0.3.0.dist-info/METADATA
llama_index_readers_youtube_metadata-0.3.0.dist-info/WHEEL
llama_index_readers_youtube_metadata-0.3.0.dist-info/RECORD
