Metadata-Version: 2.1
Name: llama-index-readers-youtube-metadata
Version: 0.3.0
Summary: llama-index readers youtube-metadata integration
License: MIT
Author: Troy Lowry
Author-email: troy@lowry.net
Requires-Python: >=3.9,<4.0
Classifier: License :: OSI Approved :: MIT License
Classifier: Programming Language :: Python :: 3
Classifier: Programming Language :: Python :: 3.9
Classifier: Programming Language :: Python :: 3.10
Classifier: Programming Language :: Python :: 3.11
Classifier: Programming Language :: Python :: 3.12
Requires-Dist: llama-index-core (>=0.12.0,<0.13.0)
Requires-Dist: youtube-transcript-api (>=0.6.2,<0.7.0)
